examples/__init__.py
examples/another_exclusion_example.py
examples/basic_usage.py
examples/boundary_exclusion_test.py
examples/boundary_inclusion_fix_test.py
examples/chainable_layout_example.py
examples/color_basic_test.py
examples/color_name_example.py
examples/color_test.py
examples/debug_ocr.py
examples/direct_ocr_test.py
examples/direct_paddle_test.py
examples/direct_qa_example.py
examples/docling_comprehensive_test.py
examples/docling_example.py
examples/docling_hierarchy_example.py
examples/docling_text_sources.py
examples/document_layout_analysis.py
examples/document_qa_example.py
examples/exclusion_count_debug.py
examples/exclusion_debug.py
examples/exclusion_example.py
examples/exclusion_optimization_example.py
examples/extract_text_test.py
examples/font_aware_example.py
examples/font_variant_example.py
examples/footer_overlap_test.py
examples/highlight_all_example.py
examples/highlight_attributes_test.py
examples/highlight_confidence_display.py
examples/highlight_demo.py
examples/highlight_float_test.py
examples/highlight_test.py
examples/highlighting_example.py
examples/image_width_example.py
examples/improved_api_example.py
examples/improved_qa_example.py
examples/layout_confidence_display_test.py
examples/layout_confidence_test.py
examples/layout_coordinate_debug.py
examples/layout_highlight_test.py
examples/logging_example.py
examples/ocr_comprehensive.py
examples/ocr_debug_example.py
examples/ocr_default_test.py
examples/ocr_engine_comparison.py
examples/ocr_example.py
examples/ocr_simplified_params.py
examples/ocr_visualization.py
examples/ocr_visualization_test.py
examples/paddle_layout_example.py
examples/paddle_layout_simple.py
examples/paddleocr_example.py
examples/page_collection_example.py
examples/polygon_highlight_example.py
examples/position_methods_example.py
examples/region_boundary_test.py
examples/region_exclusion_test.py
examples/region_expand_example.py
examples/region_image_example.py
examples/region_ocr_test.py
natural_pdf-25.3.17.2.dist-info/LICENSE
natural_pdf-25.3.17.2.dist-info/METADATA
natural_pdf-25.3.17.2.dist-info/WHEEL
natural_pdf-25.3.17.2.dist-info/top_level.txt
natural_pdf-25.3.17.2.dist-info/RECORD
