Metadata-Version: 2.2
Name: natural-pdf
Version: 25.3.17.2
Summary: A more intuitive interface for working with PDFs
Home-page: https://github.com/jsoma/natural-pdf
Author: Jonathan Soma
Author-email: jonathan.soma@gmail.com
Classifier: Programming Language :: Python :: 3
Classifier: License :: OSI Approved :: MIT License
Classifier: Operating System :: OS Independent
Requires-Python: >=3.7
License-File: LICENSE
Requires-Dist: pdfplumber>=0.7.0
Requires-Dist: Pillow>=8.0.0
Requires-Dist: colour>=0.1.5
Requires-Dist: numpy>=1.20.0
Requires-Dist: urllib3>=1.26.0
Requires-Dist: doclayout_yolo>=0.0.3
Requires-Dist: torch>=2.0.0
Requires-Dist: torchvision>=0.15.0
Requires-Dist: transformers>=4.30.0
Requires-Dist: huggingface_hub>=0.19.0
Provides-Extra: easyocr
Requires-Dist: easyocr>=1.7.0; extra == "easyocr"
Provides-Extra: paddle
Requires-Dist: paddlepaddle>=2.5.0; extra == "paddle"
Requires-Dist: paddleocr>=2.7.0; extra == "paddle"
Provides-Extra: qa
Provides-Extra: core
Requires-Dist: pdfplumber>=0.7.0; extra == "core"
Requires-Dist: Pillow>=8.0.0; extra == "core"
Requires-Dist: colour>=0.1.5; extra == "core"
Requires-Dist: numpy>=1.20.0; extra == "core"
Provides-Extra: ai
Requires-Dist: doclayout_yolo>=0.0.3; extra == "ai"
Requires-Dist: torch>=2.0.0; extra == "ai"
Requires-Dist: torchvision>=0.15.0; extra == "ai"
Requires-Dist: transformers>=4.30.0; extra == "ai"
Requires-Dist: huggingface_hub>=0.19.0; extra == "ai"
Provides-Extra: all
Requires-Dist: easyocr>=1.7.0; extra == "all"
Requires-Dist: paddlepaddle>=2.5.0; extra == "all"
Requires-Dist: paddleocr>=2.7.0; extra == "all"
Dynamic: author
Dynamic: author-email
Dynamic: classifier
Dynamic: description
Dynamic: description-content-type
Dynamic: home-page
Dynamic: provides-extra
Dynamic: requires-dist
Dynamic: requires-python
Dynamic: summary
